flask_devices.py
setup.py
Flask_Devices.egg-info/PKG-INFO
Flask_Devices.egg-info/SOURCES.txt
Flask_Devices.egg-info/dependency_links.txt
Flask_Devices.egg-info/not-zip-safe
Flask_Devices.egg-info/requires.txt
Flask_Devices.egg-info/top_level.txt