Metadata-Version: 1.1
Name: Flask-Devices
Version: 0.0.1
Summary: Flask extension for switching template folder automatically by User Agent
Home-page: https://github.com/yasunori/flask-devices
Author: Yasunori Gotoh
Author-email: yasunori@gotoh.me
License: BSD
Platform: any
Classifier: Development Status :: 4 - Beta
Classifier: Environment :: Web Environment
Classifier: Programming Language :: Python
Classifier: Topic :: Internet :: WWW/HTTP :: Dynamic Content
